iac_summarizer/__init__.py
iac_summarizer/main.py
iac_summarizer/prompts.py
iac_summarizer-2025.12.21180340.dist-info/METADATA
iac_summarizer-2025.12.21180340.dist-info/WHEEL
iac_summarizer-2025.12.21180340.dist-info/top_level.txt
iac_summarizer-2025.12.21180340.dist-info/RECORD
