Metadata-Version: 2.4
Name: iac-summarizer
Version: 2025.12.21180340
Summary: A new package that analyzes technical arguments and extracts structured summaries from text discussions about infrastructure-as-code practices. It takes user-provided text (such as forum posts, articl
Author-email: iac-summarizer <hi@eugene.plus>
License: MIT
Project-URL: Homepage, https://github.com/chigwell/iac-summarizer
Requires-Python: >=3.9
Requires-Dist: langchain-llm7>=0.0.0
Requires-Dist: llmatch-messages>=0.0.0
Requires-Dist: langchain-core>=0.3.0
